Metadata-Version: 1.2
Name: pluginable
Version: 0.1.0
Summary: Tiny but safe toolbox, for bringing a plugins system to your application.
Home-page: https://github.com/williamfzc/pluginable
Author: williamfzc
Author-email: fengzc@vip.qq.com
License: MIT
Platform: UNKNOWN
Classifier: License :: OSI Approved :: MIT License
Classifier: Programming Language :: Python
Classifier: Programming Language :: Python :: 3
Classifier: Programming Language :: Python :: 3.6
Classifier: Programming Language :: Python :: 3.7
Classifier: Programming Language :: Python :: 3.8
Requires-Python: >=3.6
